pyGoogleTranslate/__init__.py
pyGoogleTranslate/internal/__init__.py
pyGoogleTranslate/internal/caching.py
pyGoogleTranslate/internal/chrome_executable.py
pyGoogleTranslate/internal/domain.py
pyGoogleTranslate/internal/google_translate_data.py
pyGoogleTranslate/internal/language_code.py
pyGoogleTranslate/internal/pyGoogleTranslate_pyppeteer.py
pyGoogleTranslate/internal/project/alpha/text_to_speech.py
pyGoogleTranslate/internal/translation_caches/translation_caches.animenosekai_caches
pyGoogleTranslate-3.6.5.dist-info/LICENSE
pyGoogleTranslate-3.6.5.dist-info/METADATA
pyGoogleTranslate-3.6.5.dist-info/WHEEL
pyGoogleTranslate-3.6.5.dist-info/top_level.txt
pyGoogleTranslate-3.6.5.dist-info/RECORD
