Metadata-Version: 2.1
Name: pyGoogleTranslate
Version: 3.6.5
Summary: A python module which lets you use Google Translate (translation, transliteration, defintion, language detection, etc.) by parsing the website.
Home-page: https://github.com/Animenosekai/pyGoogleTranslate
Author: Anime no Sekai
Author-email: niichannomail@gmail.com
License: MIT
Download-URL: https://github.com/Animenosekai/pyGoogleTranslate/archive/v3.6.5.tar.gz
Keywords: translate,translation,google_translate,google,selenium,animenosekai
Platform: UNKNOWN
Classifier: Development Status :: 5 - Production/Stable
Classifier: License :: OSI Approved :: MIT License
Classifier: Programming Language :: Python :: 3
Classifier: Programming Language :: Python :: 3.4
Classifier: Programming Language :: Python :: 3.5
Classifier: Programming Language :: Python :: 3.6
Classifier: Programming Language :: Python :: 3.7
Classifier: Programming Language :: Python :: 3.8
Requires-Dist: selenium
Requires-Dist: lifeeasy
Requires-Dist: psutil
Requires-Dist: pyppeteer
